LICENSE
MANIFEST.in
README.md
setup.cfg
setup.py
aws_status/__init__.py
aws_status/feed.py
aws_status/status_page.py
aws_status.egg-info/PKG-INFO
aws_status.egg-info/SOURCES.txt
aws_status.egg-info/dependency_links.txt
aws_status.egg-info/requires.txt
aws_status.egg-info/top_level.txt
bin/aws-status-check
bin/aws-status-list