Metadata-Version: 1.1
Name: aws-status
Version: 0.0.13
Summary: Wraps AWS status informations obtained via the status page.
Home-page: http://github.com/jbbarth/aws-status
Author: Jean-Baptiste Barth
Author-email: jeanbaptiste.barth@gmail.com
License: MIT
Platform: UNKNOWN
Classifier: Development Status :: 4 - Beta
Classifier: Environment :: Console
Classifier: Intended Audience :: System Administrators
Classifier: License :: OSI Approved :: MIT License
Classifier: Operating System :: POSIX
Classifier: Programming Language :: Python
Classifier: Topic :: System :: Monitoring
